[{"igdb_id":154301,"name":"女孩与七匹狼","summary":"This is a horror decryption game It depicts a girl searching the house for information to decrypt Scenes are small for a house and may be updated with multiple scenes for a clue to a scene The game is not saved and must be completed once","genres":["Indie"],"developers":[],"publishers":[],"aggregated_rating":null,"release_date":1625702400,"platforms":["PC (Microsoft Windows)"],"cover_url":"//images.igdb.com/igdb/image/upload/t_thumb/co5jui.jpg","external_ids":[]}]