[{"igdb_id":114957,"name":"机退怪兽","summary":null,"genres":["Strategy","Adventure","Indie"],"developers":[],"publishers":["Surefire.Games"],"aggregated_rating":null,"release_date":1556064000,"platforms":["PC (Microsoft Windows)"],"cover_url":"//images.igdb.com/igdb/image/upload/t_thumb/cob4x5.jpg","external_ids":[{"category":null,"store":"store_None","uid":"1021670","url":"https://store.steampowered.com/app/1021670"},{"category":null,"store":"store_None","uid":"492216086","url":"https://www.twitch.tv/directory/game/%E6%9C%BA%E9%80%80%E6%80%AA%E5%85%BD"}]}]