[{"igdb_id":100095,"name":"5X","summary":null,"genres":[],"developers":[],"publishers":[],"aggregated_rating":null,"release_date":null,"platforms":[],"cover_url":null,"external_ids":[]},{"igdb_id":355941,"name":"5.x Rock Climbing","summary":null,"genres":[],"developers":[],"publishers":[],"aggregated_rating":null,"release_date":null,"platforms":[],"cover_url":null,"external_ids":[]},{"igdb_id":213081,"name":"5 x Solitaire Collection","summary":"Get 5 solitaire collections, which includes a total of 100 popular variants of FreeCell, Spider, Klondike, Canfield & Forty Thieves.","genres":["Strategy","Indie","Card & Board Game"],"developers":["eSolutions Nordic"],"publishers":["eSolutions Nordic"],"aggregated_rating":null,"release_date":null,"platforms":["Linux","PC (Microsoft Windows)","Mac"],"cover_url":"//images.igdb.com/igdb/image/upload/t_thumb/co52le.jpg","external_ids":[]},{"igdb_id":88672,"name":"5x Qube : addictive puzzle grid fill 10/10","summary":"5x Qube is an engaging puzzle game with a very unique and simple gameplay. The easy to learn and fun to master gameplay makes 5x Qube! the perfect desktop puzzle game.","genres":["Puzzle"],"developers":[],"publishers":[],"aggregated_rating":null,"release_date":null,"platforms":["Mac"],"cover_url":null,"external_ids":[]}]